{
	"animations": [
		{
			"loop": false,
			"offsets": [
				0,
				0
			],
			"anim": "Hey",
			"fps": 24,
			"name": "hey",
			"indices": []
		},
		{
			"offsets": [
				0,
				0
			],
			"loop": false,
			"fps": 24,
			"anim": "danceLeft",
			"indices": [
				1,
				2,
				3,
				4,
				5,
				6,
				7,
				8,
				9,
				10,
				11,
				12,
				13,
				14
			],
			"name": "idle"
		},
		{
			"offsets": [
				0,
				0
			],
			"loop": false,
			"fps": 24,
			"anim": "danceRight",
			"indices": [
				15,
				16,
				17,
				18,
				19,
				20,
				21,
				22,
				23,
				24,
				25,
				26,
				27,
				28,
				29,
				30
			],
			"name": "idle"
		},
		{
			"loop": false,
			"offsets": [
				0,
				0
			],
			"anim": "Sad",
			"fps": 24,
			"name": "sad",
			"indices": [
				0,
				1,
				2,
				3,
				4,
				5,
				6,
				7,
				8,
				9,
				10,
				11,
				12,
				13,
				14,
				14,
				14,
				14,
				14,
				14
			]
		}
	],
	"vocals_file": "",
	"no_antialiasing": false,
	"image": "characters/stella",
	"position": [
		-70,
		90
	],
	"healthicon": "stellatoriel",
	"flip_x": false,
	"healthbar_colors": [
		233,
		179,
		95
	],
	"camera_position": [
		0,
		0
	],
	"sing_duration": 6.1,
	"scale": 1,
	"_editor_isPlayer": false
}